{
  "name": "Thermal Combustion",
  "description": "Produces power in hot locations.",
  "type": "ThermalGenerator",
  "attribute": "heat",
  "size": 2,
  "powerProduction": 1.55,
  "category": "power",
  "research": "x-biomechanical-generator",
  "drawer": {
    "type": "DrawMulti",
    "drawers": [
      {
        "type": "DrawDefault" 
      },
      {
        "type": "DrawGlowRegion",
        "suffix": "-glow",
        "color": "ef5350"
      }
    ]
  },
  "requirements": [
    {
      "item": "x-compressed-metal",
      "amount": 75
    },
    {
      "item": "graphite",
      "amount": 50
    },
    {
      "item": "tungsten",
      "amount": 80
    },
    {
      "item": "chromium",
      "amount": 20
    }
  ]
}
